autocti/__init__.py
autocti/exc.py
autocti/fixtures.py
autocti/mock.py
autocti/preloads.py
autocti/charge_injection/__init__.py
autocti/charge_injection/ci_util.py
autocti/charge_injection/fit.py
autocti/charge_injection/hyper.py
autocti/charge_injection/layout.py
autocti/charge_injection/master.py
autocti/charge_injection/ou_sim_ci.py
autocti/charge_injection/imaging/__init__.py
autocti/charge_injection/imaging/imaging.py
autocti/charge_injection/imaging/settings.py
autocti/charge_injection/imaging/simulator.py
autocti/charge_injection/mock/__init__.py
autocti/charge_injection/mock/mock_result.py
autocti/charge_injection/model/__init__.py
autocti/charge_injection/model/analysis.py
autocti/charge_injection/model/result.py
autocti/charge_injection/model/visualizer.py
autocti/charge_injection/plot/__init__.py
autocti/charge_injection/plot/fit_ci_plotters.py
autocti/charge_injection/plot/imaging_ci_plotters.py
autocti/clocker/__init__.py
autocti/clocker/abstract.py
autocti/clocker/one_d.py
autocti/clocker/two_d.py
autocti/config/general.yaml
autocti/config/notation.yaml
autocti/config/visualize.yaml
autocti/config/priors/ccd.yaml
autocti/config/priors/hyper.yaml
autocti/config/priors/traps.yaml
autocti/cosmics/__init__.py
autocti/cosmics/cosmics.py
autocti/cosmics/cr_distances.py
autocti/cosmics/cr_lengths.py
autocti/dataset_1d/__init__.py
autocti/dataset_1d/fit.py
autocti/dataset_1d/dataset_1d/__init__.py
autocti/dataset_1d/dataset_1d/dataset_1d.py
autocti/dataset_1d/dataset_1d/settings.py
autocti/dataset_1d/dataset_1d/simulator.py
autocti/dataset_1d/model/__init__.py
autocti/dataset_1d/model/analysis.py
autocti/dataset_1d/model/result.py
autocti/dataset_1d/model/visualizer.py
autocti/dataset_1d/plot/__init__.py
autocti/dataset_1d/plot/dataset_1d_plotters.py
autocti/dataset_1d/plot/fit_plotters.py
autocti/extract/__init__.py
autocti/extract/one_d/__init__.py
autocti/extract/one_d/abstract.py
autocti/extract/one_d/eper.py
autocti/extract/one_d/fpr.py
autocti_no_gsl-2023.1.15.1.dist-info/LICENSE
autocti_no_gsl-2023.1.15.1.dist-info/METADATA
autocti_no_gsl-2023.1.15.1.dist-info/WHEEL
autocti_no_gsl-2023.1.15.1.dist-info/top_level.txt
autocti_no_gsl-2023.1.15.1.dist-info/RECORD
