Metadata-Version: 2.1
Name: autocti-no-gsl
Version: 2023.1.15.1
Summary: PyAutoCTI: Charge Transfer Inefficiency Modeling
Home-page: https://github.com/jammy2211/PyAutoCTI
Author: James Nightingale, Richard Massey, Jacob Kegerreis and Richard Hayes
Author-email: james.w.nightingale@durham.ac.uk
License: MIT License
Keywords: cli
Classifier: Intended Audience :: Science/Research
Classifier: Topic :: Scientific/Engineering :: Physics
Classifier: License :: OSI Approved :: MIT License
Classifier: Natural Language :: English
Classifier: Operating System :: OS Independent
Classifier: Programming Language :: Python :: 3.7
Classifier: Programming Language :: Python :: 3.8
Classifier: Programming Language :: Python :: 3.9
Classifier: Programming Language :: Python :: 3.10
Requires-Python: >=3.7
License-File: LICENSE
Requires-Dist: arcticpy-no-gsl (==2.1)
Requires-Dist: autoconf (==2023.1.15.1)
Requires-Dist: autofit (==2023.1.15.1)
Requires-Dist: autoarray (==2023.1.15.1)
